README.rst
setup.py
angular2tmpl/__init__.py
angular2tmpl/core.py
angular2tmpl/jinja2.py
angular2tmpl/module.py
angular2tmpl.egg-info/PKG-INFO
angular2tmpl.egg-info/SOURCES.txt
angular2tmpl.egg-info/dependency_links.txt
angular2tmpl.egg-info/requires.txt
angular2tmpl.egg-info/top_level.txt
angular2tmpl/modules/__init__.py
angular2tmpl/modules/ng.py
angular2tmpl/modules/noscript.py
bin/angular2tmpl