Metadata-Version: 1.0
Name: angular2tmpl
Version: 0.1.0
Summary: Convert AngularJS templates to Jinja2 templates for SEO.
Home-page: https://github.com/emosenkis/angular2tmpl
Author: Eitan Mosenkis
Author-email: eitan@mosenkis.net
License: MIT
Keywords: angularjs jinja2 seo
Platform: UNKNOWN
